Workbook

Sheet IMS Top final
A1: Topsheet of Total Office Expenditures Of December'25
A4: SL No | B4: Project | E4: Total
A5: 1 | B5: CLAN | E5: =CLAN!C15 -> 17580
A6: 2 | B6: IMS | E6: ='Final Total'!C18 -> 81261
A7: 3 | B7: Business Process Outsourcing | C7: Project | D7: Amount | E7: 0
C8: BHN | D8: =BHN!D13 -> 2380 | E8: =D8+D9+D10+D11+D12 -> 70344
C9: Nagad | D9: =Nagad!D12 -> 5849
C10: BAT CE | D10: ='BATB CE '!D11 -> 1580
C11: BAT PFP | D11: ='BATB PFP'!D12 -> 8500
C12: Others BPO | D12: ='BPO Final'!C18 -> 52035
A13: 4 | B13: Director's Expenditure | E13: ='Director''s Monthly Total Expens'!B9 -> 16761
B14: Total Expenses | E14: =SUM(E5:E13) -> 185946

Sheet IMS Total Expenses
A1: Topsheet of Total Office Expenditures Of December'25
A4: SL No | B4: Project | E4: Total Amount
A5: 1 | B5: CLAN | E5: =CLAN!C15 -> 17580
A6: 2 | B6: IMS | E6: ='IMS Expenses'!C17 -> 91470
A7: 3 | B7: Business Process Outsourcing | C7: Project | D7: Amount | E7: 0
C8: BHN | D8: =BHN!D13 -> 2380 | E8: =D8+D9+D10+D11+D12 -> 60135
C9: Nagad | D9: =Nagad!D12 -> 5849
C10: BAT CE | D10: ='BATB CE '!D11 -> 1580
C11: BAT PFP | D11: ='BATB PFP'!D12 -> 8500
C12: Others BPO | D12: ='BPO 1'!C17 -> 41826
A13: 4 | B13: Director's Expenditure | E13: ='Director''s Monthly Total Expens'!B9 -> 16761
B14: Total Expenses | E14: =SUM(E5:E13) -> 185946

Sheet Final Total
A2: Total Office Expenditures Of December'25
A8: SL No | B8: Purpose | C8: Total
A9: 1 | B9: Office Staff Lunch, Dinner | C9: ='Office staff food'!C13 -> 17338
A10: 2 | B10: Food For Guest | C10: ='Food for Guest '!C31 -> 10305
A11: 3 | B11: Grocery | C11: =Grocery!C30 -> 10505
A12: 4 | B12: Stationary | C12: =Stationary!C37 -> 7580
A13: 5 | B13: Others Expeses | C13: ='Office Others'!C20 -> 23689
A14: 6 | B14: Laptop Purpose | C14: ='Office Laptop '!C11 -> 0
A15: 7 | B15: Electric Purpose | C15: ='Electric purpose'!C8 -> 820
A16: 8 | B16: IMS Conveyance ( 50% of 23450/- ) | C16: =Conveyance!G71 -> 10209 | O16: P
A17: 9 | B17: Household | C17: =Household!C12 -> 815 | N17: a
B18: Total Expenses | C18: =SUM(C9:C17) -> 81261

Sheet IMS Expenses
A2: Total Office Expenditures Of December'25
A7: SL No | B7: Purpose | C7: Total
A8: 1 | B8: Office Staff Lunch, Dinner | C8: ='Office staff food'!C13 -> 17338
A9: 2 | B9: Food For Guest | C9: ='Food for Guest '!C31 -> 10305
A10: 3 | B10: Grocery | C10: =Grocery!C30 -> 10505
A11: 4 | B11: Stationary | C11: =Stationary!C37 -> 7580
A12: 5 | B12: Others Expeses | C12: ='Office Others'!C20 -> 23689
A13: 6 | B13: Laptop and Desktop Purpose | C13: ='Office Laptop '!C11 -> 0
A14: 7 | B14: Electric Purpose | C14: ='Electric purpose'!C8 -> 820
A15: 8 | B15: Conveyance | C15: =Conveyance!G70 -> 20418 | O15: P
A16: 9 | B16: Household | C16: =Household!C12 -> 815 | N16: a
B17: Total Expenses | C17: =SUM(C8:C16) -> 91470

Sheet Food for Guest 
A1: Food For Guest Of December'25
A8: Date | B8: Items | C8: Amount (TK)
A9: 45992 | B9: Food for Guest for BATB Client | C9: 1680
A10: 45998 | B10: Food for Guest for Weeding purpose | C10: 1880
A11: 45998 | B11: Food for Guest for Audit Client | C11: 615
A12: 45999 | B12: Food for Guest for Audit Client | C12: 495
A13: 46000 | B13: Food for Guest for Audit Client | C13: 190
A14: 46001 | B14: Food for Guest for Audit Client | C14: 190
A15: 46002 | B15: Food for Guest for Audit Client | C15: 205
A16: 46005 | B16: Food for Guest for Audit Client | C16: 275
A17: 46012 | B17: Food for Guest for Audit Client | C17: 705
A18: 46014 | B18: Food for Guest for Artist purpose | C18: 500
A19: 46014 | B19: Food for Guest for Weeding purpose | C19: 1180
A20: 46019 | B20: Food for Guest for Audit Client | C20: 205
... A22: 46022 | B22: Food for Guest for Audit Client | C22: 425
A23: 46023 | B23: Food for Guest for IFFAD group | C23: =SUM(C9:C22) -> 10305
A24: 46024 | B24: Food for Guest for IFFAD group
A25: 46025 | B25: Food for Guest for IFFAD group
A26: 46026 | B26: Food for Guest for IFFAD group
A27: 46027 | B27: Food for Guest for IFFAD group
A28: 46028 | B28: Food for Guest for IFFAD group
A29: 46029 | B29: Food for Guest for IFFAD group
A30: 46030 | B30: Food for Guest for IFFAD group
C31: =SUM(C9:C22) -> 10305

Sheet Office staff food
A1: Food for Office Staff Of December'25
A7: Date | B7: Items | C7: Amount (TK)
A8: 45992 | B8: Lunch Purpose for Four Office Staff (Shohag,Lipon,Shathi,Jahangir & Rakibul) for the month of December 2025 (2000*3= 6000, 1500*1=1500 ) | C8: 7500
A9: 45993 | B9: Lunch Purpose for Four Office Staff Lipon for the month of December 2025 | C9: 2500
A10: 45993 | B10: Birthday Cake | C10: 2390
A11: 46021 | B11: Food for Sumon | C11: 260
A12: 46021 | B12: Office staff late night dinner purposeKitkat event purpose | C12: 4688
C13: =SUM(C8:C12) -> 17338

Sheet Grocery
A1: Groceries Expenditure Of December'25
A9: DATE | B9: ITEMS | C9: AMOUNT(tk)
A10: 43374 | B10: Groceries Expenditure for the September'18
A11: 43405 | B11: Tessue box,Danish,Hand wash,Wheel powder,Rok,Harpic,Napkin,
A12: 43406 | B12: Aoutomatic Air freshner with refill for Head office
A13: 45992 | B13: Harpic, Harpic powder,Toilet Tessue, Vim bar, Vim liquid, Sugar,Arosol, Tessue Box | C13: 4172
A14: 45995 | B14: Air freshner | C14: 600
A15: 45995 | B15: Ginger for HO half KG | C15: 90
A16: 45998 | B16: Lizol, Rok, Vim powder | C16: 548
A17: 46005 | B17: Ginger for HO half KG | C17: 90
A18: 46008 | B18: Danish,Sugar | C18: 4885
A19: 46011 | B19: Ginger for HO half KG | C19: 20
A20: 46019 | B20: Ginger for HO half KG | C20: 100
A21: 46011
A22: 46012
A23: 46013
A24: 46014
A25: 46015
A26: 46016
A27: 46017
A28: 46018
A29: 46019
C30: =SUM(C11:C29) -> 10505

Sheet Stationary
A1: Stationary Expenditure Of December'25
A4: DATE | B4: ITEMS | C4: Amount (TK)
A5: 43374 | B5: A4 Paper 15 Rims | C5: 4200
A6: 43375 | B6: Lazer book for Godown purpose
A7: 45993 | B7: A4 Paper 9 pcs | C7: 3510
A8: 46000 | B8: Marker pen | C8: 480
A9: 46000 | B9: Stationary Items | C9: 630
A10: 46005 | B10: Compose for Harun Bhai | C10: 500
A11: 46008 | B11: Seal Making | C11: 1200
A12: 46008 | B12: Mushok book for Head office | C12: 860
A13: 46009 | B13: A4 paper | C13: 400
A14: 46004 | C14: =SUM(C7:C13) -> 7580
A15: 46005
A16: 46006
A17: 46007
A18: 46008
A19: 46009
A20: 46010
A21: 46011
A22: 46012
A23: 46013
A24: 46014
A25: 46015
A26: 46016
... A36: 46026
C37: =SUM(C7:C13) -> 7580

Sheet Office Others
B1: Other Expenditures Of December'25 (Head Office)
A4: DATE | B4: ITEMS | C4: Amount (TK)
A5: 45992 | B5: Internet bill for Creative Canvas,Elite Communication and Dtech for Tasfir, Sohel & Mahmud for the month of December'25 | C5: 9500
A6: 45993 | B6: ID card for Naima | C6: 180
A7: 45994 | B7: Mobileile recharge & Data purpose for Shohag and Lipon for the month of December 2025 | C7: 817
A8: 45994 | B8: SSL for Sakib | C8: 400
A9: 45997 | B9: Jali And Cement for Comon Toilet | C9: 150
A10: 45998 | B10: Risk assurance fee for Credit card bill | C10: 620
A11: 45999 | B11: Lock open purpose for Harun Bhai Room | C11: 200
A12: 46002 | B12: IP Comunication for Head office for the month of December 2025 | C12: 3675
A13: 46005 | B13: MS Office 360 for One Year | C13: 1200
A14: 46009 | B14: Donation for Milon Mela for Hizra | C14: 500
A15: 46009 | B15: Lock open purpose for Harun Bhai Room | C15: 250 | J15: p
A16: 46014 | B16: Tanni Of Accounts Medical Treatment Purpose | C16: 5000
A17: 46020 | B17: Courier Purpose | C17: 445
A18: 46023 | B18: Cleaner's service charge purpose for the month of December'25 for Head Office | C18: 350
A19: 46023 | B19: News Paper bill service charge purpose for the month of December'25 for Head Office | C19: 402
C20: =SUM(C5:C19) -> 23689

Sheet Office Laptop 
A1: Laptop Purpose For the month Of December'25
A7: DATE | B7: ITEMS | C7: Amount (TK)
A8: 45992 | B8: Hard disk and SATA SSD for Pavel bhai
A9: 45993 | B9: FICE studio networking TP-Link Desktop switch, UPS for new PC for Studio, Patch cable CAT-6 For studio
A10: 45994 | B10: BASUS USB Typr-C Cable for Sami Boss
C11: =SUM(C8:C10) -> 0

Sheet Conveyance
A1: Conveyance For the Month of December'25
A5: Date | B5: Name | C5: Designation | D5: Place | E5: Media | F5: From Whom | G5: Amount
A6: 45992 | B6: Mojnu | C6: Office Assistant | D6: Office to Niketon to Boss house Banani to IMS | E6: Rickshaw | F6: Harun Bhai | G6: 260
A7: 45992 | B7: Lipon | C7: Office Assistant | D7: Office to SIBL to IMS TO SJIBL to IMS | E7: Rickshaw | F7: Harun Bhai | G7: 410
A8: 45992 | B8: Momin | C8: Office Assistant | D8: Office to Vat Office to Smart School to Office | E8: Rickshaw | F8: Harun Bhai | G8: 170
A9: 45993 | B9: Mojnu | C9: Office Assistant | D9: Office to DBBL to DHL to IMS | E9: Rickshaw, | F9: Harun Bhai | G9: 170
A10: 45993 | B10: Momin | C10: Office Assistant | D10: Office to SIBL to DHL to IMS | E10: Rickshaw | F10: Harun Bhai | G10: 210
A11: 45993 | B11: Lipon | C11: Office Assistant | D11: Office to SIBL to IMS TO SJIBL to IMS | E11: Bike | F11: Harun Bhai | G11: 510
A12: 45994 | B12: Mojnu | C12: Office Assistant | D12: Office to DBBL to IMS | E12: Bike | F12: Harun Bhai | G12: 300
A13: 45995 | B13: Shohag | C13: Office Assistant | D13: Office to Mirpur DOSH to office to SJIBL to Office | E13: Bike, Rikshaw | F13: Harun Bhai | G13: 430
A14: 45995 | B14: Shathi | C14: Office Assistant | D14: Office to Nagad to Office | E14: Rickshaw | F14: Harun Bhai | G14: 140
A15: 45995 | B15: Lipon | C15: Office Assistant | D15: Office to IPDC to office to SJIBL to Nestle to IMS | E15: Rickshaw | F15: Harun Bhai | G15: 350
A16: 45997 | B16: Mojnu | C16: Office Assistant | D16: Office to DBBL to GP to IMS | E16: Rickshaw | F16: Harun Bhai | G16: 120
A17: 45997 | B17: Momin | C17: Office Assistant | D17: Office to Vat Office to Smart School to Office | E17: Rickshaw | F17: Harun Bhai | G17: 710
... A41: 46009 | B41: Harun | C41: G. Manager | D41: IMS to UBL to IMS | E41: Uber | F41: Harun Bhai | G41: 668
A42: 46009 | B42: Nazmus Sakib | C42: Assistant Manager | D42: Office to FICCI Event of Nestle to Office to IMS | E42: Uber | F42: Harun Bhai | G42: 290 | I42: l
A43: 46009 | B43: Mojnu | C43: Office Assistant | D43: Office to Banglalink to IMS | E43: Rickshaw | F43: Harun Bhai | G43: 770
A44: 46011 | B44: Shohag | C44: Office Assistant | D44: Office to GP Office to SJIBL to Office | E44: Rickshaw | F44: Harun Bhai | G44: 300
A45: 46011 | B45: Momin | C45: Office Assistant | D45: Office to DBH to SJIBL to BAT to Banani bazar to DBBL to IMS | E45: Rickshaw | F45: Harun Bhai | G45: 120
A46: 46012 | B46: Lipon | C46: Office Assistant | D46: IMS to Share on banani to VAT office to DBBL to IMS | E46: Rickshaw | F46: Harun Bhai | G46: 220
A47: 46012 | B47: Lipon | C47: Office Assistant | D47: IMS to Share on banani to CBC office to DBBL to IMS | E47: Rickshaw | F47: Harun Bhai | G47: 470
A48: 46012 | B48: Shohag | C48: Office Assistant | D48: Office to SJIBL to office(4 times ) | E48: Rickshaw,Car | F48: Harun Bhai | G48: 190
A49: 46013 | B49: Mojnu | C49: Office Assistant | D49: Office to Banglalink to SJIBL to IMS | E49: Rickshaw,Car | F49: Harun Bhai | G49: 260
A50: 46014 | B50: Shohag | C50: IT Manager | D50: Office to Mirpur to Global to IMS | E50: Rickshaw,CNG | F50: Harun Bhai | G50: 220
A51: 46014 | B51: Siam | C51: Senior Executive | D51: Office to VAT Office to Mohakhali to IMS | E51: Rickshaw | F51: Harun Bhai | G51: 140
A52: 46015 | B52: Lipon | C52: Office Assistant | D52: Office to SJIBL to Sami Boss house to IMS | E52: Rickshaw | F52: Harun Bhai | G52: 470
A53: 46015 | B53: Mojnu | C53: Office Assistant | D53: Office to Banglalink to SJIBL to IMS | E53: Rickshaw | F53: Harun Bhai | G53: 190
A54: 46015 | B54: Tamanna | C54: Office Assistant | D54: Office to Uniliver to SJIBL to BAT to Banani | E54: Rickshaw | F54: Harun Bhai | G54: 280
... A69: 46052 | B69: Shohag | C69: Office Assistant | D69: Office to Uniliver to BAT to DBBL to IMS | E69: Rickshaw | F69: Harun Bhai | G69: 170
F70: Total | G70: =SUM(G6:G69) -> 20418
D71: 50% of Total Amount for BPO | G71: =G70/2 -> 10209

Sheet Electric purpose
A1: Electric Purpose Of December'25
A5: DATE | B5: ITEMS | C5: Amount (TK) | M5: p
A6: 45994 | B6: LED light for HO kitchen | C6: 320
A7: 46012 | B7: Gree AC Remote | C7: 500
C8: =SUM(C6:C7) -> 820

Sheet Household
A1: Household For Head Office Of December'25
A9: DATE | B9: ITEMS | C9: Amount (TK)
A10: 45994 | B10: Mop, Odonil, Majoni, for HO | C10: 815
C12: =SUM(C10:C11) -> 815

Sheet Director's Monthly Total Expens
A1: MD and Director's Expenses for the Month of December'25
J3: .
A6: For Whom | B6: Total TK
A7: MD Boss Expenditures for the month of December'25 | B7: ='[1]MD''s Expenses of Dec''25'!D18 -> 9801
A8: Director Sami Boss Expenditures for the month of December'25 | B8: ='[1]Director''s Expenses Dec''25'!D12 -> 6960
B9: =SUM(B7,B8) -> 16761

Sheet CLAN
A1: CLAN Project Expenditures December'25
A6: SL No | B6: Purpose | C6: Total
A7: 1 | B7: CLAN Others Expenses | C7: ='[2] Others Expenses'!D12 -> 7603
A8: 2 | B8: CLAN Laptop Expenses | C8: ='[2]Laptop Expenses'!D11 -> 0
A9: 3 | B9: CLAN Purpose Food Expenses | C9: ='[2]Food Expenses'!D13 -> 5775
A10: 4 | B10: CLAN Purpose Grocery Expenses | C10: =[2]Grocery!C35 -> 3812
A11: 5 | B11: CLAN Purpose HouseHold Expenses | C11: ='[2]House Hold'!C9 -> 0
A12: 6 | B12: CLAN Purpose Electric Purpose Expenses | C12: ='[2]Electric Purpose'!C9 -> 0
A13: 7 | B13: CLAN Conveyance | C13: =[2]Conveyance!G14 -> 0
A14: 8 | B14: CLAN Purpose Stationary Expenses | C14: =[2]Stationary!C24 -> 390
C15: =SUM(C7:C14) -> 17580

Sheet BATB CE 
A1: BATB CE Project Other Of December'25
A8: Date | B8: Project Name | C8: Items | D8: Amount (TK)
A9: 46004 | B9: BATB CE | C9: A4 paper 2pcs for BAT CE project | D9: 800
A10: 46004 | B10: BATB CE | C10: AC Service charge | D10: 780
D11: =SUM(D9:D10) -> 1580

Sheet BATB PFP
A1: BATB PFP Project Others Expenses Of December'25
A9: Date | B9: Project Name | C9: Items | D9: Amount (TK)
A10: 46021 | B10: BATB PFP | C10: Administrative Cost of BATB PFP Project pay out call for the month of December 2025 | D10: 8500
D12: =SUM(D10:D11) -> 8500

Sheet BHN
A1: BHN Project Others Expenses Of December'25
A10: DATE | B10: Project Name | C10: ITEMS | D10: Amount (TK)
A11: 46082 | B11: BHN | C11: Ara Water Jar 34 pcs for the month of December 2025 | D11: =34*70 -> 2380
D13: =SUM(D11:D12) -> 2380

Sheet Nagad
A1: Nagad Project Others Of December'25
A6: DATE | B6: Project Name | C6: ITEMS | D6: Amount (TK)
A7: 45995 | B7: Nagad | C7: A4 paper & Pen for Nagad Project | D7: 450
A8: 45996 | B8: Nagad | C8: Air freshner,Teabag, Sugar,NapkinTessue, ,Hand wash, Vim bar, Toilet Tessue,Milk Powder, Vim Bar, Ginger | D8: 2780
A9: 46000 | B9: Nagad | C9: ID card for Asif | D9: 180
A10: 46005 | B10: Nagad | C10: Carnival Internet bill for the month of December 2025 | D10: 1599
A11: 46025 | B11: Nagad | C11: Ara Pure drinking water 12 pcs for Nagad the month of Decemberber'25 | D11: =12*70 -> 840
D12: =SUM(D7:D11) -> 5849

Sheet BPO 1
A1: Project Total Expenditure For the Month of December'25
A7: SL No | B7: Project | C7: Total
A8: 1 | B8: Project Purpose Other Expenses | C8: ='[3]Project Others'!E13 -> 15580
A9: 2 | B9: Project Food Purpose | C9: ='[3]Project Purpose Food'!E8 -> 2500
A10: 3 | B10: Project Laptop Purpose | C10: ='[3]Project Purpose Laptop'!E9 -> 6200
A11: 4 | B11: Project Conveyance Purpose | C11: ='[3]Project Conveyance'!G16 -> 5679
A12: 5 | B12: Project Guest | C12: ='[3]Project Guest'!D11 -> 2165
A13: 6 | B13: Project Household | C13: ='[3]Project House Hold'!D12 -> 0
A14: 7 | B14: Project Electric purpose | C14: ='[3]Project Electric'!D11 -> 670
A15: 8 | B15: Project Grocery Purpose | C15: ='[3]Project Grocery'!C15 -> 2752
A16: 9 | B16: Project Stationary purpose | C16: ='[3]Project Stationary'!C12 -> 6280
C17: =SUM(C8:C16) -> 41826

Sheet BPO Final
A1: Project Total Expenditure For the Month of December'25
A7: SL No | B7: Project | C7: Total
A8: 1 | B8: Project Purpose Other Expenses | C8: ='[3]Project Others'!E13 -> 15580
A9: 2 | B9: Project Food | C9: ='[3]Project Purpose Food'!E8 -> 2500
A10: 3 | B10: Project Laptop | C10: ='[3]Project Purpose Laptop'!E9 -> 6200
A11: 4 | B11: Project Conveyance | C11: ='[3]Project Conveyance'!G16 -> 5679
A12: 5 | B12: Project Guest | C12: ='[3]Project Guest'!D11 -> 2165
A13: 6 | B13: Project Household | C13: ='[3]Project House Hold'!D12 -> 0
A14: 7 | B14: Project Electric | C14: ='[3]Project Electric'!D11 -> 670
A15: 8 | B15: Project Grocery | C15: ='[3]Project Grocery'!C15 -> 2752
A16: 9 | B16: Project Stationary | C16: ='[3]Project Stationary'!C12 -> 6280
A17: 10 | B17: Total (20418/-) IMS 50% Conveyance | C17: ='[3]Convayance IMS'!G71 -> 10209
C18: =SUM(C8:C17) -> 52035

Sheet Forecast Films
A1: Forecast Project All Expenses Of September'24
A6: DATE | B6: Project Name | C6: ITEMS | D6: Amount (TK)
B7: Forecast | C7: Air freshner, Tessue box
D8: 0
D9: =SUM(D7:D8) -> 0
